LICENSE
README.md
setup.cfg
setup.py
eks_node_migrator.egg-info/PKG-INFO
eks_node_migrator.egg-info/SOURCES.txt
eks_node_migrator.egg-info/dependency_links.txt
eks_node_migrator.egg-info/entry_points.txt
eks_node_migrator.egg-info/requires.txt
eks_node_migrator.egg-info/top_level.txt
eksmigrator/__init__.py
eksmigrator/__main__.py
eksmigrator/_version.py
eksmigrator/cli.py
eksmigrator/config.py
eksmigrator/lib/__init__.py
eksmigrator/lib/aws.py
eksmigrator/lib/exceptions.py
eksmigrator/lib/k8s.py
eksmigrator/lib/logger.py