Metadata-Version: 2.1
Name: eks-node-migrator
Version: 1.0.5
Summary: EKS Node Migrator is a utility for to gracefully drain self-managed EKS node groups. Primarly used for draining workload from on-demand/reserverd instances so it can be scheduled over SPOT instance backed nodegroups.
Home-page: https://github.com/ahrizvi/eks-node-migrator
Author: Anfal Haider
Author-email: anfal.haider@careem.com
Maintainer: Anfal Haider
Maintainer-email: anfal.haider@careem.com
License: Apache License, Version 2.0
Platform: UNKNOWN
Classifier: Development Status :: 3 - Alpha
Classifier: Environment :: Console
Classifier: Intended Audience :: Developers
Classifier: License :: OSI Approved :: Apache Software License
Classifier: Programming Language :: Python
Classifier: Programming Language :: Python :: 3.7
Classifier: Programming Language :: Python :: 3.8
Requires-Python: >=3.7
License-File: LICENSE
